src/macros.v
/********************* macros for debugging *************/

`define DEBUG

src/compare.v
///////////////////////////////////////////
// Module compare.v                                            
// Info:  Verilog Code for Compare
//        Cpmpares two Input to Alu for 
//        for Branch Instructions
///////////////////////////////////////////

module compare
(
    input        clk,
    input [31:0] in1,
    input [31:0] in2,
    input [2:0]   op,
    output reg out
);
    always @(posedge clk) begin
        case(op)
            3'b000:  out = (in1 == in2);                        // BEQ
            3'b001:  out = (in1 != in2);                        // BNE
            3'b100:  out = ($signed(in1) < $signed(in2));       // BLT
            3'b101:  out = ($signed(in1) >= $signed(in2));      // BGE
            3'b110:  out = (in1 < in2);                         // BLTU
            3'b111:  out = (in1 >= in2);                        // BGEU
            default: out = 1'bx;                                // Default - Dont Care
        endcase
    end

endmodule

src/alu.v
///////////////////////////////////////////
// Module alu.v                                            
// Info:  Verilog Code for ALU
//        Covers All R - Type Instructions 
///////////////////////////////////////////

module alu
(   
    input        clk,
    input [31:0] in1,
    input [31:0] in2,
    input [2:0] func3,    // Control Signal op: [14:12]
    input      opequal,   // Operation Qualification (+/-, Logical/Arithmetic)
    output reg [31:0] out // ALU result
);
    always@(posedge clk) begin
        case(func3)
            3'b000: out = opequal ? in1 - in2 : in1 + in2;                        // ADD/SUB
            3'b010: out = ($signed(in1) < $signed(in2)) ? 32'b1 : 32'b0;          // SLT
            3'b011: out = (in1 < in2) ? 32'b1 : 32'b0;                            // SLTU
            3'b100: out = in1 ^ in2;                                              // XOR
            3'b110: out = in1 | in2;                                              // OR
            3'b111: out = in1 & in2;                                              // AND
            3'b001: out = in1 << in2[4:0];                                        // SLL
            3'b101: out =  $signed({opequal ? in1[31] : 1'b0, in1}) >>> in2[4:0]; // SRL/SRA
        endcase
    end
endmodule

src/register_file.v
///////////////////////////////////////////
// Module register_file.v                                            
// Info:  Verilog Code for register_file
//        Two Combinational Read  
//        One clocked Write
///////////////////////////////////////////
`include "macros.v"

module register_file 
(     
    input             clock,             //Clock for register 
    input [4:0]       read1,             //5 Bit address of register 1
    input [4:0]       read2,             //5 Bit address of register 2
    input [4:0]    writereg,             //5 Bit Write Register Address 
    input [31:0]  writedata,             //32 Bit data for write Register
    input              inEn,             //Control Signal for regwrite

    output     [31:0] data1,             //Data 1 from register 1 
    output     [31:0] data2              //Data 2 from register 2
);
    reg [31:0] RF [31:0];                //32 Registers each 32 bits long

    assign data1 = RF[read1];            //This Requires more BRAM resulting in more LUTs
    assign data2 = RF[read2];            //BRAM is slower, one solution two banks and simultaneous write

    always@(posedge clock)
    begin
        if(inEn) begin
            if(writereg != 0) begin 
                RF[writereg] <= writedata;
            end
        end
    end 

    //-----------------------------For Debug---------------------------------
    
    `ifdef DEBUG
        integer i;

        initial begin
        RF[0] <= 32'h0000_0000;
        RF[1] <= 32'h0000_0005;
        RF[2] <= 32'h0000_0003;
        end

        always @(*) begin 
            $display("REGISTER FILE:");
            for(i = 0; i<32; i++) begin 
                $display("R[%d]     ::      %d", i, RF[i]);
            end
            $display("\n\n");
        end  
    `endif
endmodule

src/mini_decoder.v
///////////////////////////////////////////
// Module mini_decoder.v   
//                                         
// Info:  Verilog Code for mini decoder
//        Decoder for RISCV
//  
///////////////////////////////////////////

module mini_decoder
(
   input wire [31:0]          instr,          //The instruction to be deocded 
   
   output reg           writeBackEn,          //Asserted when writing to a reg
   output wire [4:0]             rd,          //The register to be written back
   output wire [4:0]            rs1,          //Register output 1
   output wire [4:0]            rs2,          //Register output 2

   output [2:0]               func3,         //Operation done by ALU
   output reg              funcQual,         //Operation Qualifier
   
   output reg [31:0]            imm          //Immediate Value decoded from the instruction
);


    //Decoding:
    assign rd        =  instr[11:7];       //Rd Register
    assign rs1       = instr[19:15];       //Rs1 Register
    assign rs2       = instr[24:20];       //Rs2 Register
    assign func3     = instr[14:12];       //Decides the operation

    /*Five Immediate formats:
    wire [31:0] Iimm = {{21{instr[31]}}, instr[30:20]};
    wire [31:0] Simm = {{21{instr[31]}}, instr[30:25], instr[11:7]};
    wire [31:0] Bimm = {{20{instr[31]}}, instr[7], instr[30:25], instr[11:8], 1'b0};
    wire [31:0] Jimm = {{12{instr[31]}}, instr[19:12], instr[20], instr[30:21], 1'b0};   
    wire [31:0] Uimm = {instr[31], instr[30:12], {12{1'b0}}};
    */

    //We need to distinguish shifts for two reasons:
    // - we need to wait for ALU when it is a shift
    // - For ALU ops with immediate: funcQual is 0
    //   EXCEPT for shifts ALU ops/funcqual :: then it is instr[30]

    wire funcisshift = (func3 == 3'b001) || (func3 == 3'b101);

    //The rest of instruction decoding, for the following signals:
    // WriteBackEn
    // funcqual

    // The Two LSBs are always 11 in the base RV32I instruction set.
    // One can also check for error when these bits are whether or zero or not

    always @(*) begin  
        if( instr[6:2] == 5'b01100) begin   // ALU operation: Register,Register
            writeBackEn =   1'b1;
            funcQual = instr[30];         
        end
    end

    //-----------------------------For Debug---------------------------------
    
    `ifdef DEBUG
        always @(*) begin 
             $display("instr: %b", instr);
            $display("Destination Register:%b", rd);
            $display("Source Register: %b", rs1);
            $display("Source Register: %b", rs2);
            $display("Func3 : %b", func3);
        end  
    `endif

endmodule

src/rv32.v
/////////////////////////////////////////////////////////////////////////
// Module rv32.v   
//                                         
// Info:  Verilog Code for rv32I
//        For R type instructions
//  
////////////////////////////////////////////////////////////////////////


`include "register_file.v"                  //32 General Purpose Registers
`include "compare.v"                        //Compare module for single bit output for branch instructions                             
`include "alu.v"                            //32 Bit ALU
`include "mini_decoder.v"                   //Mini Decoder for decoding R Type registers

module rv32
(
    input                      clk,         //Clock
    input                    reset,         //High to reset processor

    input  wire [31:0]      in_data,        //Word Read From Memory
    output reg  [31:0]     out_data,        //Word to store in memory
    output reg [31:0]  out_mem_addr,        //Memory Access address

    output reg               mem_wr,        //Memory Write
    output reg               mem_rd         //Memory Read
);
    parameter ADDR_WIDTH = 32;              //width of the the address bus

    //The Program Counter 
    reg [ADDR_WIDTH - 1:0] PC;

    //The Latched Instruction
    reg [31:0] instr;

    //Program Counter in Normal Operation (Do we need to do this directly?)
    wire [ADDR_WIDTH - 1:0] PCplus4 = PC + 4;

    ///////////////////////////////////////////////////////////////////
    // Instruction Decoding
    ////////////////////////////////////////////////////////////////////
    
    wire          writeBackEn;          //Asserted when writing to a reg
    wire [4:0] writeBackRegId;          //The register to be written back
    wire [4:0]         RegId1;          //Register output 1
    wire [4:0]         RegId2;          //Register output 2
    

    wire [2:0] 	        func3;          // operation done by the ALU, tests, load/store mode
    wire 	         funcQual;          // 'qualifier' used by some operations (+/-, logic/arith shifts)
    wire [31:0] 	      imm;          // immediate value decoded from the instruction

    mini_decoder decoder
    (
        .instr(instr),                   //The instruction to be deocded 
   
        .writeBackEn(writeBackEn),      //Asserted when writing to a reg
        .rd(writeBackRegId),            //The register to be written back
        .rs1(RegId1),                   //Register output 1
        .rs2(RegId2),                   //Register output 2

        .func3(func3),                  //Operation done by ALU
        .funcQual(funcQual),            //Operation Qualifier
   
        .imm(imm)                       //Immediate Value decoded from the instruction
    );

    ////////////////////////////////////////////////////////////////////
    // Register File
    ////////////////////////////////////////////////////////////////////
    
    wire writeBack;                     // asserted if register write back is done.
    reg  [31:0] writeBackData;
    wire [31:0] regOut1;
    wire [31:0] regOut2;

    assign writeBack = writeBackEn;
    
    register_file regs
    (     
        .clock(clk),                       //Clock for register 
        .read1(RegId1),                    //5 Bit address of register 1
        .read2(RegId2),                    //5 Bit address of register 2
        .writereg(writeBackRegId),         //5 Bit Write Register Address 
        .writedata(writeBackData),         //32 Bit data for write Register
        .inEn(writeBack),                  //Control Signal for regwrite
        .data1(regOut1),                   //Data 1 from register 1 
        .data2(regOut2)                    //Data 2 from register 2
    );

    ////////////////////////////////////////////////////////////////////
    // ALU
    ////////////////////////////////////////////////////////////////////

    wire [31:0] aluout;
    reg [31:0] aluIn1;
    reg [31:0] aluIn2;

    alu ALU
    (   
        .clk(clk),
        .in1(aluIn1),
        .in2(aluIn2),
        .func3(func3),          // Control Signal op: [14:12]
        .opequal(funcQual),     // Operation Qualification (+/-, Logical/Arithmetic)
        .out(aluout)            // ALU result
    );

    ////////////////////////////////////////////////////////////////////
    // The State Machine
    ////////////////////////////////////////////////////////////////////
    
    // The states, using 1-hot encoding (reduces both LUT count and critical path).
    reg [4:0] state;

    always @(posedge clk) begin
        state <= 0;
        mem_wr <= 0;
        mem_rd <= 0;

        //Reset Condition
        if (reset) begin
            state[0] <= 1'b1;
            PC      <= 32'b0;    
        end
        else begin 
            case(1'b1)
                //-------------------------Fetch----------------------------------
                state[0]: begin         
                    out_mem_addr <= PC;
                    mem_rd       <=  1;
                    state[1]     <=  1;
                end
                //-------------------------Delay----------------------------------                
                state[1]: begin         
                    state[2]     <=  1;
                end
                //-------------------------Decode----------------------------------   
                state[2]: begin
                    instr        <= in_data;
                    state[3]     <=  1;
                end  
                //-------------------------Execute----------------------------------   
                state[3]: begin
                    PC <= PCplus4;
                    writeBackData <= aluout;
                    aluIn1 <= regOut1;
                    aluIn2 <= regOut2;
                    state[0]     <=  1;
                end  
                default: state[0] <= 1;     
            endcase
        end
    end
endmodule

src/memory.v
/////////////////////////////////////////////////////////////////////////
// Module memory.v   
//                                         
// Info:  Verilog Code for memory
////////////////////////////////////////////////////////////////////////
`include "macros.v"

module memory
(
    input                 clk,
    input  [31:0]          PC,
    input                  rd,    //read signal
    input                  wr,    //write signal
    input  [31:0]      i_data,    //Input Data
    output reg [31:0]  o_data     //Output Data
);

    reg [31:0] memory [15:0];

    always@(posedge clk) begin
        if (wr) begin
            memory[PC] <= i_data;
        end      
        if (rd) begin
            o_data <= memory[PC];
        end 
    end

    //-----------------------------For Debug---------------------------------
    
    `ifdef DEBUG
        initial begin
            //Add (00104083)
            memory [0] = 32'h002081B3;  //func7_rs2_rs1_func3_rd_opcode
            memory [1] = 32'd0;
            memory [2] = 32'd2;
            //Subtract
            memory [4] = 32'h402081B3;  //func7_rs2_rs1_func3_rd_opcode
        /*    $display("Zeroth Location   :: %b", memory[0]);
            $display("First Location    :: %b", memory[1]);
            $display("Second Location   :: %b", memory[2]);
            $display("Fourth Location   :: %b", memory[4]);*/
        end
    `endif
endmodule

src/rv32_soc.v
/////////////////////////////////////////////////////////////////////////
// Module rv32_soc.v   
//                                         
// Info:  Verilog Code for rv32 soc 
//        (For R type instructions)
//  
////////////////////////////////////////////////////////////////////////

`include "rv32.v"                   
`include "memory.v"                   
`include "macros.v"

module rv32_soc
(
    input clk,
    input reset
);

wire [31:0] i_data, o_data;
wire mem_wr, mem_rd;
wire [31:0] PC;

memory ram
(
    .clk(clk),          //Clock
    .PC(PC),            //Address
    .rd(mem_rd),        //read signal
    .wr(mem_wr),        //write signal
    .i_data(o_data),    //Input Data
    .o_data(i_data)     //Output Data
);

rv32 core 
(
    .clk(clk),          //Clock
    .reset(reset),      //High to reset processor

    .in_data(i_data),   //Word Read From Memory
    .out_data(o_data),  //Word to store in memory
    .out_mem_addr(PC),  //Memory Access address

    .mem_wr(mem_wr),    //Memory Write
    .mem_rd(mem_rd)     //Memory Read
);

endmodule

src/rv32_soc_TB.v
/////////////////////////////////////////////////////////////////////////
// Module rv32_soc_TB.v   
//                                         
// Info:  Test bench code for rv32 soc
//        (For R type instructions)
//  
////////////////////////////////////////////////////////////////////////

`include "rv32_soc.v"
`timescale 1ns / 1ps

module rv32_soc_TB();

reg clock;
reg reset;

always begin
    clock = 1'b0;
    forever #5  clock = ~clock;
end

initial begin
    #5 reset = 1'b1;
    #5 reset = 1'b0;
    #100 $finish;
end

initial
begin
    $dumpfile("rv32_soc_TB.vcd");
    $dumpvars(0, rv32_soc_TB);
end


rv32_soc uut 
(
    .clk(clock),
    .reset(reset)
);

endmodule

src/rv32_soc_TB.vcd
$date
	Sun Feb 14 20:22:55 2021
$end
$version
	Icarus Verilog
$end
$timescale
	1ps
$end
$scope module rv32_soc_TB $end
$var reg 1 ! clock $end
$var reg 1 " reset $end
$scope module uut $end
$var wire 1 ! clk $end
$var wire 1 " reset $end
$var wire 32 # o_data [31:0] $end
$var wire 1 $ mem_wr $end
$var wire 1 % mem_rd $end
$var wire 32 & i_data [31:0] $end
$var wire 32 ' PC [31:0] $end
$scope module core $end
$var wire 1 ! clk $end
$var wire 1 " reset $end
$var wire 1 ( writeBack $end
$var wire 5 ) writeBackRegId [4:0] $end
$var wire 1 * writeBackEn $end
$var wire 32 + regOut2 [31:0] $end
$var wire 32 , regOut1 [31:0] $end
$var wire 32 - in_data [31:0] $end
$var wire 32 . imm [31:0] $end
$var wire 1 / funcQual $end
$var wire 3 0 func3 [2:0] $end
$var wire 32 1 aluout [31:0] $end
$var wire 5 2 RegId2 [4:0] $end
$var wire 5 3 RegId1 [4:0] $end
$var wire 32 4 PCplus4 [31:0] $end
$var reg 32 5 PC [31:0] $end
$var reg 32 6 aluIn1 [31:0] $end
$var reg 32 7 aluIn2 [31:0] $end
$var reg 32 8 instr [31:0] $end
$var reg 1 % mem_rd $end
$var reg 1 $ mem_wr $end
$var reg 32 9 out_data [31:0] $end
$var reg 32 : out_mem_addr [31:0] $end
$var reg 5 ; state [4:0] $end
$var reg 32 < writeBackData [31:0] $end
$scope module ALU $end
$var wire 1 ! clk $end
$var wire 32 = in1 [31:0] $end
$var wire 32 > in2 [31:0] $end
$var wire 1 / opequal $end
$var wire 3 ? func3 [2:0] $end
$var reg 32 @ out [31:0] $end
$upscope $end
$scope module decoder $end
$var wire 1 A funcisshift $end
$var wire 32 B instr [31:0] $end
$var wire 5 C rs2 [4:0] $end
$var wire 5 D rs1 [4:0] $end
$var wire 5 E rd [4:0] $end
$var wire 3 F func3 [2:0] $end
$var reg 1 / funcQual $end
$var reg 32 G imm [31:0] $end
$var reg 1 * writeBackEn $end
$upscope $end
$scope module regs $end
$var wire 1 ! clock $end
$var wire 32 H data1 [31:0] $end
$var wire 32 I data2 [31:0] $end
$var wire 1 ( inEn $end
$var wire 5 J read1 [4:0] $end
$var wire 5 K read2 [4:0] $end
$var wire 32 L writedata [31:0] $end
$var wire 5 M writereg [4:0] $end
$var integer 32 N i [31:0] $end
$upscope $end
$upscope $end
$scope module ram $end
$var wire 32 O PC [31:0] $end
$var wire 1 ! clk $end
$var wire 32 P i_data [31:0] $end
$var wire 1 % rd $end
$var wire 1 $ wr $end
$var reg 32 Q o_data [31:0] $end
$upscope $end
$upscope $end
$upscope $end
$enddefinitions $end
#0
$dumpvars
bx Q
bx P
bx O
b100000 N
bx M
bx L
bx K
bx J
bx I
bx H
bx G
bx F
bx E
bx D
bx C
bx B
xA
bx @
bx ?
bx >
bx =
bx <
bx ;
bx :
bx 9
bx 8
bx 7
bx 6
bx 5
bx 4
bx 3
bx 2
bx 1
bx 0
x/
bx .
bx -
bx ,
bx +
x*
bx )
x(
bx '
bx &
x%
x$
bx #
x"
0!
$end
#5000
b100 4
b0 5
0%
0$
b1 ;
1"
1!
#10000
0"
0!
#15000
1%
b0 '
b0 :
b0 O
b10 ;
1!
#20000
0!
#25000
b1000001000000110110011 &
b1000001000000110110011 -
b1000001000000110110011 Q
0%
b100 ;
1!
#30000
0!
#35000
0A
0/
1(
1*
b11 )
b11 E
b11 M
b101 ,
b101 H
b1 3
b1 D
b1 J
b11 +
b11 I
b10 2
b10 C
b10 K
b0 0
b0 ?
b0 F
b1000001000000110110011 8
b1000001000000110110011 B
b1000 ;
1!
#40000
0!
#45000
b11 7
b11 >
b101 6
b101 =
b1000 4
b100 5
b1 ;
1!
#50000
0!
#55000
1%
b100 '
b100 :
b100 O
b10 ;
b1000 1
b1000 @
1!
#60000
0!
#65000
b1000000001000001000000110110011 &
b1000000001000001000000110110011 -
b1000000001000001000000110110011 Q
0%
b100 ;
1!
#70000
0!
#75000
1/
b1000000001000001000000110110011 8
b1000000001000001000000110110011 B
b1000 ;
1!
#80000
0!
#85000
b1000 <
b1000 L
b1100 4
b1000 5
b1 ;
b10 1
b10 @
1!
#90000
0!
#95000
b100000 N
1%
b1000 '
b1000 :
b1000 O
b10 ;
1!
#100000
0!
#105000
bx &
bx -
bx Q
0%
b100 ;
1!
