src/macros.v
/********************* macros for debugging *************/

`define DEBUG

src/compare.v
///////////////////////////////////////////
// Module compare.v                                            
// Info:  Verilog Code for Compare
//        Cpmpares two Input to Alu for 
//        for Branch Instructions
///////////////////////////////////////////

module compare
(
    input        clk,
    input [31:0] in1,
    input [31:0] in2,
    input [2:0]   op,
    output reg out
);
    always @(posedge clk) begin
        case(op)
            3'b000:  out = (in1 == in2);                        // BEQ
            3'b001:  out = (in1 != in2);                        // BNE
            3'b100:  out = ($signed(in1) < $signed(in2));       // BLT
            3'b101:  out = ($signed(in1) >= $signed(in2));      // BGE
            3'b110:  out = (in1 < in2);                         // BLTU
            3'b111:  out = (in1 >= in2);                        // BGEU
            default: out = 1'bx;                                // Default - Dont Care
        endcase
    end

endmodule

src/alu.v
///////////////////////////////////////////
// Module alu.v                                            
// Info:  Verilog Code for ALU
//        Covers All R - Type Instructions 
///////////////////////////////////////////

module alu
(   
    input        clk,
    input [31:0] in1,
    input [31:0] in2,
    input [2:0] func3,    // Control Signal op: [14:12]
    input      opequal,   // Operation Qualification (+/-, Logical/Arithmetic)
    output reg [31:0] out // ALU result
);
    always@(posedge clk) begin
        case(func3)
            3'b000: out = opequal ? in1 - in2 : in1 + in2;                        // ADD/SUB
            3'b010: out = ($signed(in1) < $signed(in2)) ? 32'b1 : 32'b0;          // SLT
            3'b011: out = (in1 < in2) ? 32'b1 : 32'b0;                            // SLTU
            3'b100: out = in1 ^ in2;                                              // XOR
            3'b110: out = in1 | in2;                                              // OR
            3'b111: out = in1 & in2;                                              // AND
            3'b001: out = in1 << in2[4:0];                                        // SLL
            3'b101: out =  $signed({opequal ? in1[31] : 1'b0, in1}) >>> in2[4:0]; // SRL/SRA
        endcase
    end
endmodule

src/register_file.v
///////////////////////////////////////////
// Module register_file.v                                            
// Info:  Verilog Code for register_file
//        Two Combinational Read  
//        One clocked Write
///////////////////////////////////////////
`include "macros.v"

module register_file 
(     
    input             clock,             //Clock for register 
    input [4:0]       read1,             //5 Bit address of register 1
    input [4:0]       read2,             //5 Bit address of register 2
    input [4:0]    writereg,             //5 Bit Write Register Address 
    input [31:0]  writedata,             //32 Bit data for write Register
    input              inEn,             //Control Signal for regwrite

    output     [31:0] data1,             //Data 1 from register 1 
    output     [31:0] data2              //Data 2 from register 2
);
    reg [31:0] RF [31:0];                //32 Registers each 32 bits long

    assign data1 = RF[read1];            //This Requires more BRAM resulting in more LUTs
    assign data2 = RF[read2];            //BRAM is slower, one solution two banks and simultaneous write

    always@(posedge clock)
    begin
        if(inEn) begin
            if(writereg != 0) begin 
                RF[writereg] <= writedata;
            end
        end
    end 

    //-----------------------------For Debug---------------------------------
    
    `ifdef DEBUG
        integer i;

        initial begin
        RF[0] <= 32'h0000_0000;
        RF[1] <= 32'h0000_0005;
        RF[2] <= 32'h0000_0003;
        end

        always @(*) begin 
            $display("REGISTER FILE:");
            for(i = 0; i<32; i++) begin 
                $display("R[%d]     ::      %d", i, RF[i]);
            end
            $display("\n\n");
        end  
    `endif
endmodule

src/mini_decoder.v
///////////////////////////////////////////
// Module mini_decoder.v   
//                                         
// Info:  Verilog Code for mini decoder
//        Decoder for RISCV
//  
///////////////////////////////////////////

module mini_decoder
(
   input wire [31:0]          instr,          //The instruction to be deocded 
   
   output reg           writeBackEn,          //Asserted when writing to a reg
   output wire [4:0]             rd,          //The register to be written back
   output wire [4:0]            rs1,          //Register output 1
   output wire [4:0]            rs2,          //Register output 2

   output [2:0]               func3,         //Operation done by ALU
   output reg              funcQual,         //Operation Qualifier
   
   output reg [31:0]            imm          //Immediate Value decoded from the instruction
);


    //Decoding:
    assign rd        =  instr[11:7];       //Rd Register
    assign rs1       = instr[19:15];       //Rs1 Register
    assign rs2       = instr[24:20];       //Rs2 Register
    assign func3     = instr[14:12];       //Decides the operation

    /*Five Immediate formats:
    wire [31:0] Iimm = {{21{instr[31]}}, instr[30:20]};
    wire [31:0] Simm = {{21{instr[31]}}, instr[30:25], instr[11:7]};
    wire [31:0] Bimm = {{20{instr[31]}}, instr[7], instr[30:25], instr[11:8], 1'b0};
    wire [31:0] Jimm = {{12{instr[31]}}, instr[19:12], instr[20], instr[30:21], 1'b0};   
    wire [31:0] Uimm = {instr[31], instr[30:12], {12{1'b0}}};
    */

    //We need to distinguish shifts for two reasons:
    // - we need to wait for ALU when it is a shift
    // - For ALU ops with immediate: funcQual is 0
    //   EXCEPT for shifts ALU ops/funcqual :: then it is instr[30]

    wire funcisshift = (func3 == 3'b001) || (func3 == 3'b101);

    //The rest of instruction decoding, for the following signals:
    // WriteBackEn
    // funcqual

    // The Two LSBs are always 11 in the base RV32I instruction set.
    // One can also check for error when these bits are whether or zero or not

    always @(*) begin  
        if( instr[6:2] == 5'b01100) begin   // ALU operation: Register,Register
            writeBackEn =   1'b1;
            funcQual = instr[30];         
        end
    end

    //-----------------------------For Debug---------------------------------
    
    `ifdef DEBUG
        always @(*) begin 
             $display("instr: %b", instr);
            $display("Destination Register:%b", rd);
            $display("Source Register: %b", rs1);
            $display("Source Register: %b", rs2);
            $display("Func3 : %b", func3);
        end  
    `endif

endmodule

src/rv32.v
/////////////////////////////////////////////////////////////////////////
// Module rv32.v   
//                                         
// Info:  Verilog Code for rv32I
//        For R type instructions
//  
////////////////////////////////////////////////////////////////////////


`include "register_file.v"                  //32 General Purpose Registers
`include "compare.v"                        //Compare module for single bit output for branch instructions                             
`include "alu.v"                            //32 Bit ALU
`include "mini_decoder.v"                   //Mini Decoder for decoding R Type registers

module rv32
(
    input                      clk,         //Clock
    input                    reset,         //High to reset processor

    input  wire [31:0]      in_data,        //Word Read From Memory
    output reg  [31:0]     out_data,        //Word to store in memory
    output reg [31:0]  out_mem_addr,        //Memory Access address

    output reg               mem_wr,        //Memory Write
    output reg               mem_rd         //Memory Read
);
    parameter ADDR_WIDTH = 32;              //width of the the address bus

    //The Program Counter 
    reg [ADDR_WIDTH - 1:0] PC;

    //The Latched Instruction
    reg [31:0] instr;

    //Program Counter in Normal Operation (Do we need to do this directly?)
    wire [ADDR_WIDTH - 1:0] PCplus4 = PC + 4;

    ///////////////////////////////////////////////////////////////////
    // Instruction Decoding
    ////////////////////////////////////////////////////////////////////
    
    wire          writeBackEn;          //Asserted when writing to a reg
    wire [4:0] writeBackRegId;          //The register to be written back
    wire [4:0]         RegId1;          //Register output 1
    wire [4:0]         RegId2;          //Register output 2
    

    wire [2:0] 	        func3;          // operation done by the ALU, tests, load/store mode
    wire 	         funcQual;          // 'qualifier' used by some operations (+/-, logic/arith shifts)
    wire [31:0] 	      imm;          // immediate value decoded from the instruction

    mini_decoder decoder
    (
        .instr(instr),                   //The instruction to be deocded 
   
        .writeBackEn(writeBackEn),      //Asserted when writing to a reg
        .rd(writeBackRegId),            //The register to be written back
        .rs1(RegId1),                   //Register output 1
        .rs2(RegId2),                   //Register output 2

        .func3(func3),                  //Operation done by ALU
        .funcQual(funcQual),            //Operation Qualifier
   
        .imm(imm)                       //Immediate Value decoded from the instruction
    );

    ////////////////////////////////////////////////////////////////////
    // Register File
    ////////////////////////////////////////////////////////////////////
    
    wire writeBack; // asserted if register write back is done.
    reg  [31:0] writeBackData;
    wire [31:0] regOut1;
    wire [31:0] regOut2;

    register_file regs
    (     
        .clock(clk),                       //Clock for register 
        .read1(RegId1),                    //5 Bit address of register 1
        .read2(RegId2),                    //5 Bit address of register 2
        .writereg(writeBackRegId),         //5 Bit Write Register Address 
        .writedata(writeBackData),         //32 Bit data for write Register
        .inEn(writeBack),                  //Control Signal for regwrite
        .data1(regOut1),                   //Data 1 from register 1 
        .data2(regOut2)                    //Data 2 from register 2
    );

    ////////////////////////////////////////////////////////////////////
    // ALU
    ////////////////////////////////////////////////////////////////////

    wire [31:0] aluout;
    wire [31:0] aluIn1;
    wire [31:0] aluIn2;

    alu ALU
    (   
        .clk(clk),
        .in1(aluIn1),
        .in2(aluIn2),
        .func3(func3),          // Control Signal op: [14:12]
        .opequal(funcQual),     // Operation Qualification (+/-, Logical/Arithmetic)
        .out(aluout)            // ALU result
    );

    ////////////////////////////////////////////////////////////////////
    // The State Machine
    ////////////////////////////////////////////////////////////////////
    
    // The states, using 1-hot encoding (reduces both LUT count and critical path).
    reg [4:0] state;

    always @(posedge clk) begin
        state <= 0;
        mem_wr <= 0;
        mem_rd <= 0;

        //Reset Condition
        if (reset) begin
            state[0] <= 1'b1;
            PC      <= 32'b0;    
        end
        else begin 
            case(1'b1)
                //-------------------------Fetch----------------------------------
                state[0]: begin         
                    out_mem_addr <= PC;
                    mem_rd       <=  1;
                    state[1]     <=  1;
                end
                //-------------------------Delay----------------------------------                
                state[1]: begin         
                    state[2]     <=  1;
                end
                //-------------------------Decode----------------------------------   
                state[2]: begin
                    instr        <= in_data;
                    state[3]     <=  1;
                end  
                //-------------------------Execute----------------------------------   
                state[3]: begin
                    PC <= PCplus4;
                    writeBackData <= aluout;
                    state[0]     <=  1;
                end  
                default: state[0] <= 1;     
            endcase
        end
    end
endmodule

src/memory.v
/////////////////////////////////////////////////////////////////////////
// Module memory.v   
//                                         
// Info:  Verilog Code for memory
////////////////////////////////////////////////////////////////////////
`include "macros.v"

module memory
(
    input                 clk,
    input  [31:0]          PC,
    input                  rd,    //read signal
    input                  wr,    //write signal
    input  [31:0]      i_data,    //Input Data
    output reg [31:0]  o_data     //Output Data
);

    reg [31:0] memory [15:0];

    always@(posedge clk) begin
        if (wr) begin
            memory[PC] <= i_data;
        end      
        if (rd) begin
            o_data <= memory[PC];
        end 
    end

    //-----------------------------For Debug---------------------------------
    
    `ifdef DEBUG
        initial begin
            memory [0] = 32'h002081B3;  //Add
            memory [1] = 32'h402081B3;  //Subtract
            memory [2] = 32'h002091B3;  //sll
            memory [3] = 32'h0020A1B3;  //slt
            memory [4] = 32'h0020B1B3;  //sltu
            memory [5] = 32'h0020C1B3;  //xor
            memory [6] = 32'h0020D1B3;  //srl
            memory [7] = 32'h4020D1B3;  //sra
            memory [8] = 32'h0020E1B3;  //or 
            memory [9] = 32'h0020F1B3;  //and
        /*    $display("Zeroth Location   :: %b", memory[0]);
            $display("First Location    :: %b", memory[1]);
            $display("Second Location   :: %b", memory[2]);
            $display("Fourth Location   :: %b", memory[4]);*/
        end
    `endif
endmodule

src/rv32_soc.v
/////////////////////////////////////////////////////////////////////////
// Module rv32_soc.v   
//                                         
// Info:  Verilog Code for rv32 soc 
//        (For R type instructions)
//  
////////////////////////////////////////////////////////////////////////

`include "rv32.v"                   
`include "memory.v"                   
`include "macros.v"

module rv32_soc
(
    input clk,
    input reset
);

wire [31:0] i_data, o_data;
wire mem_wr, mem_rd;
wire [31:0] PC;

memory ram
(
    .clk(clk),          //Clock
    .PC(PC),            //Address
    .rd(mem_rd),        //read signal
    .wr(mem_wr),        //write signal
    .i_data(o_data),    //Input Data
    .o_data(i_data)     //Output Data
);

rv32 core 
(
    .clk(clk),          //Clock
    .reset(reset),      //High to reset processor

    .in_data(i_data),   //Word Read From Memory
    .out_data(o_data),  //Word to store in memory
    .out_mem_addr(PC),  //Memory Access address

    .mem_wr(mem_wr),    //Memory Write
    .mem_rd(mem_rd)     //Memory Read
);

endmodule

src/rv32_soc_TB.v
/////////////////////////////////////////////////////////////////////////
// Module rv32_soc_TB.v   
//                                         
// Info:  Test bench code for rv32 soc
//        (For R type instructions)
//  
////////////////////////////////////////////////////////////////////////

`include "rv32_soc.v"
`timescale 1ns / 1ps

module rv32_soc_TB();

reg clock;
reg reset;

always begin
    clock = 1'b0;
    forever #5  clock = ~clock;
end

initial begin
    #5 reset = 1'b1;
    #5 reset = 1'b0;
    #1000 $finish;
end

initial
begin
    $dumpfile("rv32_soc_TB.vcd");
    $dumpvars(0, rv32_soc_TB);
end


rv32_soc uut 
(
    .clk(clock),
    .reset(reset)
);

endmodule

src/rv32_soc_TB.vcd
$date
	Mon Feb 15 19:48:12 2021
$end
$version
	Icarus Verilog
$end
$timescale
	1ps
$end
$scope module rv32_soc_TB $end
$var reg 1 ! clock $end
$var reg 1 " reset $end
$scope module uut $end
$var wire 1 ! clk $end
$var wire 1 " reset $end
$var wire 32 # o_data [31:0] $end
$var wire 1 $ mem_wr $end
$var wire 1 % mem_rd $end
$var wire 32 & i_data [31:0] $end
$var wire 32 ' PC [31:0] $end
$scope module core $end
$var wire 1 ! clk $end
$var wire 1 " reset $end
$var wire 1 ( writeBack $end
$var wire 5 ) writeBackRegId [4:0] $end
$var wire 1 * writeBackEn $end
$var wire 32 + regOut2 [31:0] $end
$var wire 32 , regOut1 [31:0] $end
$var wire 32 - in_data [31:0] $end
$var wire 32 . imm [31:0] $end
$var wire 1 / funcQual $end
$var wire 3 0 func3 [2:0] $end
$var wire 32 1 aluout [31:0] $end
$var wire 5 2 RegId2 [4:0] $end
$var wire 5 3 RegId1 [4:0] $end
$var wire 32 4 PCplus4 [31:0] $end
$var reg 32 5 PC [31:0] $end
$var reg 32 6 aluIn1 [31:0] $end
$var reg 32 7 aluIn2 [31:0] $end
$var reg 32 8 instr [31:0] $end
$var reg 1 % mem_rd $end
$var reg 1 $ mem_wr $end
$var reg 32 9 out_data [31:0] $end
$var reg 32 : out_mem_addr [31:0] $end
$var reg 5 ; state [4:0] $end
$var reg 32 < writeBackData [31:0] $end
$scope module ALU $end
$var wire 1 ! clk $end
$var wire 32 = in1 [31:0] $end
$var wire 32 > in2 [31:0] $end
$var wire 1 / opequal $end
$var wire 3 ? func3 [2:0] $end
$var reg 32 @ out [31:0] $end
$upscope $end
$scope module decoder $end
$var wire 1 A funcisshift $end
$var wire 32 B instr [31:0] $end
$var wire 5 C rs2 [4:0] $end
$var wire 5 D rs1 [4:0] $end
$var wire 5 E rd [4:0] $end
$var wire 3 F func3 [2:0] $end
$var reg 1 / funcQual $end
$var reg 32 G imm [31:0] $end
$var reg 1 * writeBackEn $end
$upscope $end
$scope module regs $end
$var wire 1 ! clock $end
$var wire 32 H data1 [31:0] $end
$var wire 32 I data2 [31:0] $end
$var wire 1 ( inEn $end
$var wire 5 J read1 [4:0] $end
$var wire 5 K read2 [4:0] $end
$var wire 32 L writedata [31:0] $end
$var wire 5 M writereg [4:0] $end
$var integer 32 N i [31:0] $end
$upscope $end
$upscope $end
$scope module ram $end
$var wire 32 O PC [31:0] $end
$var wire 1 ! clk $end
$var wire 32 P i_data [31:0] $end
$var wire 1 % rd $end
$var wire 1 $ wr $end
$var reg 32 Q o_data [31:0] $end
$upscope $end
$upscope $end
$upscope $end
$enddefinitions $end
#0
$dumpvars
bx Q
bx P
bx O
b100000 N
bx M
bx L
bx K
bx J
bx I
bx H
bx G
bx F
bx E
bx D
bx C
bx B
xA
bx @
bx ?
bx >
bx =
bx <
bx ;
bx :
bx 9
bx 8
bx 7
bx 6
bx 5
bx 4
bx 3
bx 2
bx 1
bx 0
x/
bx .
bx -
bx ,
bx +
x*
bx )
x(
bx '
bx &
x%
x$
bx #
x"
0!
$end
#5000
b1 4
b0 5
0%
0$
b1 ;
1"
1!
#10000
0"
0!
#15000
1%
b0 '
b0 :
b0 O
b10 ;
1!
#20000
0!
#25000
b1000001000000110110011 &
b1000001000000110110011 -
b1000001000000110110011 Q
0%
b100 ;
1!
#30000
0!
#35000
0A
0/
1(
1*
b11 )
b11 E
b11 M
b101 ,
b101 H
b1 3
b1 D
b1 J
b11 +
b11 I
b10 2
b10 C
b10 K
b0 0
b0 ?
b0 F
b1000001000000110110011 8
b1000001000000110110011 B
b1000 ;
1!
#40000
0!
#45000
b11 7
b11 >
b101 6
b101 =
b10 4
b1 5
b1 ;
1!
#50000
0!
#55000
1%
b1 '
b1 :
b1 O
b10 ;
b1000 1
b1000 @
1!
#60000
0!
#65000
b1000000001000001000000110110011 &
b1000000001000001000000110110011 -
b1000000001000001000000110110011 Q
0%
b100 ;
1!
#70000
0!
#75000
1/
b1000000001000001000000110110011 8
b1000000001000001000000110110011 B
b1000 ;
1!
#80000
0!
#85000
b1000 <
b1000 L
b11 4
b10 5
b1 ;
b10 1
b10 @
1!
#90000
0!
#95000
b100000 N
1%
b10 '
b10 :
b10 O
b10 ;
1!
#100000
0!
#105000
b1000001001000110110011 &
b1000001001000110110011 -
b1000001001000110110011 Q
0%
b100 ;
1!
#110000
0!
#115000
1A
0/
b1 0
b1 ?
b1 F
b1000001001000110110011 8
b1000001001000110110011 B
b1000 ;
1!
#120000
0!
#125000
b10 <
b10 L
b100 4
b11 5
b1 ;
b101000 1
b101000 @
1!
#130000
0!
#135000
b100000 N
1%
b11 '
b11 :
b11 O
b10 ;
1!
#140000
0!
#145000
b1000001010000110110011 &
b1000001010000110110011 -
b1000001010000110110011 Q
0%
b100 ;
1!
#150000
0!
#155000
0A
b10 0
b10 ?
b10 F
b1000001010000110110011 8
b1000001010000110110011 B
b1000 ;
1!
#160000
0!
#165000
b101000 <
b101000 L
b101 4
b100 5
b1 ;
b0 1
b0 @
1!
#170000
0!
#175000
b100000 N
1%
b100 '
b100 :
b100 O
b10 ;
1!
#180000
0!
#185000
b1000001011000110110011 &
b1000001011000110110011 -
b1000001011000110110011 Q
0%
b100 ;
1!
#190000
0!
#195000
b11 0
b11 ?
b11 F
b1000001011000110110011 8
b1000001011000110110011 B
b1000 ;
1!
#200000
0!
#205000
b0 <
b0 L
b110 4
b101 5
b1 ;
1!
#210000
0!
#215000
b100000 N
1%
b101 '
b101 :
b101 O
b10 ;
1!
#220000
0!
#225000
b1000001100000110110011 &
b1000001100000110110011 -
b1000001100000110110011 Q
0%
b100 ;
1!
#230000
0!
#235000
b100 0
b100 ?
b100 F
b1000001100000110110011 8
b1000001100000110110011 B
b1000 ;
1!
#240000
0!
#245000
b111 4
b110 5
b1 ;
b110 1
b110 @
1!
#250000
0!
#255000
1%
b110 '
b110 :
b110 O
b10 ;
1!
#260000
0!
#265000
b1000001101000110110011 &
b1000001101000110110011 -
b1000001101000110110011 Q
0%
b100 ;
1!
#270000
0!
#275000
1A
b101 0
b101 ?
b101 F
b1000001101000110110011 8
b1000001101000110110011 B
b1000 ;
1!
#280000
0!
#285000
b110 <
b110 L
b1000 4
b111 5
b1 ;
b0 1
b0 @
1!
#290000
0!
#295000
b100000 N
1%
b111 '
b111 :
b111 O
b10 ;
1!
#300000
0!
#305000
b1000000001000001101000110110011 &
b1000000001000001101000110110011 -
b1000000001000001101000110110011 Q
0%
b100 ;
1!
#310000
0!
#315000
1/
b1000000001000001101000110110011 8
b1000000001000001101000110110011 B
b1000 ;
1!
#320000
0!
#325000
b0 <
b0 L
b1001 4
b1000 5
b1 ;
1!
#330000
0!
#335000
b100000 N
1%
b1000 '
b1000 :
b1000 O
b10 ;
1!
#340000
0!
#345000
b1000001110000110110011 &
b1000001110000110110011 -
b1000001110000110110011 Q
0%
b100 ;
1!
#350000
0!
#355000
0A
0/
b110 0
b110 ?
b110 F
b1000001110000110110011 8
b1000001110000110110011 B
b1000 ;
1!
#360000
0!
#365000
b1010 4
b1001 5
b1 ;
b111 1
b111 @
1!
#370000
0!
#375000
1%
b1001 '
b1001 :
b1001 O
b10 ;
1!
#380000
0!
#385000
b1000001111000110110011 &
b1000001111000110110011 -
b1000001111000110110011 Q
0%
b100 ;
1!
#390000
0!
#395000
b111 0
b111 ?
b111 F
b1000001111000110110011 8
b1000001111000110110011 B
b1000 ;
1!
#400000
0!
#405000
b111 <
b111 L
b1011 4
b1010 5
b1 ;
b1 1
b1 @
1!
#410000
0!
#415000
b100000 N
1%
b1010 '
b1010 :
b1010 O
b10 ;
1!
#420000
0!
#425000
bx &
bx -
bx Q
0%
b100 ;
1!
#430000
0!
#435000
xA
bx )
bx E
bx M
bx ,
bx H
bx 3
bx D
bx J
bx +
bx I
bx 2
bx C
bx K
bx 0
bx ?
bx F
bx 8
bx B
b1000 ;
1!
#440000
0!
#445000
bx 7
bx >
bx 6
bx =
b1 <
b1 L
b1100 4
b1011 5
b1 ;
1!
#450000
0!
#455000
1%
b1011 '
b1011 :
b1011 O
b10 ;
1!
#460000
0!
#465000
0%
b100 ;
1!
#470000
0!
#475000
b1000 ;
1!
#480000
0!
#485000
b1101 4
b1100 5
b1 ;
1!
#490000
0!
#495000
1%
b1100 '
b1100 :
b1100 O
b10 ;
1!
#500000
0!
#505000
0%
b100 ;
1!
#510000
0!
#515000
b1000 ;
1!
#520000
0!
#525000
b1110 4
b1101 5
b1 ;
1!
#530000
0!
#535000
1%
b1101 '
b1101 :
b1101 O
b10 ;
1!
#540000
0!
#545000
0%
b100 ;
1!
#550000
0!
#555000
b1000 ;
1!
#560000
0!
#565000
b1111 4
b1110 5
b1 ;
1!
#570000
0!
#575000
1%
b1110 '
b1110 :
b1110 O
b10 ;
1!
#580000
0!
#585000
0%
b100 ;
1!
#590000
0!
#595000
b1000 ;
1!
#600000
0!
#605000
b10000 4
b1111 5
b1 ;
1!
#610000
0!
#615000
1%
b1111 '
b1111 :
b1111 O
b10 ;
1!
#620000
0!
#625000
0%
b100 ;
1!
#630000
0!
#635000
b1000 ;
1!
#640000
0!
#645000
b10001 4
b10000 5
b1 ;
1!
#650000
0!
#655000
1%
b10000 '
b10000 :
b10000 O
b10 ;
1!
#660000
0!
#665000
0%
b100 ;
1!
#670000
0!
#675000
b1000 ;
1!
#680000
0!
#685000
b10010 4
b10001 5
b1 ;
1!
#690000
0!
#695000
1%
b10001 '
b10001 :
b10001 O
b10 ;
1!
#700000
0!
#705000
0%
b100 ;
1!
#710000
0!
#715000
b1000 ;
1!
#720000
0!
#725000
b10011 4
b10010 5
b1 ;
1!
#730000
0!
#735000
1%
b10010 '
b10010 :
b10010 O
b10 ;
1!
#740000
0!
#745000
0%
b100 ;
1!
#750000
0!
#755000
b1000 ;
1!
#760000
0!
#765000
b10100 4
b10011 5
b1 ;
1!
#770000
0!
#775000
1%
b10011 '
b10011 :
b10011 O
b10 ;
1!
#780000
0!
#785000
0%
b100 ;
1!
#790000
0!
#795000
b1000 ;
1!
#800000
0!
#805000
b10101 4
b10100 5
b1 ;
1!
#810000
0!
#815000
1%
b10100 '
b10100 :
b10100 O
b10 ;
1!
#820000
0!
#825000
0%
b100 ;
1!
#830000
0!
#835000
b1000 ;
1!
#840000
0!
#845000
b10110 4
b10101 5
b1 ;
1!
#850000
0!
#855000
1%
b10101 '
b10101 :
b10101 O
b10 ;
1!
#860000
0!
#865000
0%
b100 ;
1!
#870000
0!
#875000
b1000 ;
1!
#880000
0!
#885000
b10111 4
b10110 5
b1 ;
1!
#890000
0!
#895000
1%
b10110 '
b10110 :
b10110 O
b10 ;
1!
#900000
0!
#905000
0%
b100 ;
1!
#910000
0!
#915000
b1000 ;
1!
#920000
0!
#925000
b11000 4
b10111 5
b1 ;
1!
#930000
0!
#935000
1%
b10111 '
b10111 :
b10111 O
b10 ;
1!
#940000
0!
#945000
0%
b100 ;
1!
#950000
0!
#955000
b1000 ;
1!
#960000
0!
#965000
b11001 4
b11000 5
b1 ;
1!
#970000
0!
#975000
1%
b11000 '
b11000 :
b11000 O
b10 ;
1!
#980000
0!
#985000
0%
b100 ;
1!
#990000
0!
#995000
b1000 ;
1!
#1000000
0!
#1005000
b11010 4
b11001 5
b1 ;
1!
